typedAPI/__init__.py
typedAPI/log_config.py
typedAPI/server.py
typedAPI/body/__init__.py
typedAPI/body/schema.py
typedAPI/body/service.py
typedAPI/endpoint/__init__.py
typedAPI/endpoint/data.py
typedAPI/endpoint/guards.py
typedAPI/endpoint/schema.py
typedAPI/endpoint/service.py
typedAPI/headers/__init__.py
typedAPI/headers/data.py
typedAPI/headers/factory.py
typedAPI/headers/schema.py
typedAPI/headers/service.py
typedAPI/resource_path/__init__.py
typedAPI/resource_path/data.py
typedAPI/resource_path/schema.py
typedAPI/resource_path/service.py
typedAPI/response/__init__.py
typedAPI/response/data.py
typedAPI/response/factory.py
typedAPI/response/factory_tests.py
typedAPI/response/guards.py
typedAPI/response/guards_tests.py
typedAPI/response/processors.py
typedAPI/response/schema.py
typedAPI/response/service.py
typedAPI/response/service_tests.py
typed_api_framework-0.0.0.dist-info/LICENSE
typed_api_framework-0.0.0.dist-info/METADATA
typed_api_framework-0.0.0.dist-info/WHEEL
typed_api_framework-0.0.0.dist-info/top_level.txt
typed_api_framework-0.0.0.dist-info/RECORD
