Metadata-Version: 2.1
Name: typed-api-framework
Version: 0.0.0
Summary: A lightweigt package for concisely defining an api.
Home-page: https://github.com/Digital-Defiance/typed-api
Author: Rui Filipe de Sousa Campos @ Digital Defiance
Author-email: mail@ruicampos.org
Classifier: Development Status :: 3 - Alpha
Classifier: License :: OSI Approved :: MIT License
Classifier: Programming Language :: Python :: 3
Classifier: Programming Language :: Python :: 3.6
Classifier: Programming Language :: Python :: 3.7
Classifier: Programming Language :: Python :: 3.8
Classifier: Programming Language :: Python :: 3.9
Classifier: Programming Language :: Python :: 3.10
Classifier: Programming Language :: Python :: 3.11
License-File: LICENSE
